astro_pi_replay/__init__.py
astro_pi_replay/configuration.py
astro_pi_replay/custom_types.py
astro_pi_replay/downloader.py
astro_pi_replay/exception.py
astro_pi_replay/executor.py
astro_pi_replay/main.py
astro_pi_replay/self_updater.py
astro_pi_replay/venv_resolver.py
astro_pi_replay/version_utils.py
astro_pi_replay/libcamera/__init__.py
astro_pi_replay/libcamera/libcamera/__init__.py
astro_pi_replay/libcamera/libcamera/_libcamera/__init__.py
astro_pi_replay/libcamera/libcamera/_libcamera/transform.py
astro_pi_replay/libcamera/libcamera/_libcamera/controls/__init__.py
astro_pi_replay/libcamera/libcamera/_libcamera/controls/controls.py
astro_pi_replay/orbit/__init__.py
astro_pi_replay/orbit/motion_sensor.py
astro_pi_replay/orbit/telemetry.py
astro_pi_replay/orbit/telemetry_adapter.py
astro_pi_replay/picamera/__init__.py
astro_pi_replay/picamera/abstract_camera.py
astro_pi_replay/picamera/array.py
astro_pi_replay/picamera/camera.py
astro_pi_replay/picamera/color.py
astro_pi_replay/picamera/encoders.py
astro_pi_replay/picamera/exc.py
astro_pi_replay/picamera/exif.py
astro_pi_replay/picamera/frames.py
astro_pi_replay/picamera/mmalobj.py
astro_pi_replay/picamera/preview.py
astro_pi_replay/picamera/renderers.py
astro_pi_replay/picamera/streams.py
astro_pi_replay/picamera/original/streams.py
astro_pi_replay/picamzero/ImageWrapper.py
astro_pi_replay/picamzero/PicameraZeroException.py
astro_pi_replay/picamzero/__init__.py
astro_pi_replay/picamzero/camera_adapter.py
astro_pi_replay/picamzero/utilities.py
astro_pi_replay/preview/preview.py
astro_pi_replay/preview/teardown_protocol.py
astro_pi_replay/resources/AstroPi_2021_colour.png
astro_pi_replay/resources/ISS.OEM_J2K_EPH.txt
astro_pi_replay/resources/__init__.py
astro_pi_replay/resources/de421.bsp
astro_pi_replay/resources/iss.txt
astro_pi_replay/resources/metadata_schema.json
astro_pi_replay/resources/motd
astro_pi_replay/resources/sequences.csv
astro_pi_replay/resources/utils.py
astro_pi_replay-1.0.1.dist-info/LICENCE.txt
astro_pi_replay-1.0.1.dist-info/METADATA
astro_pi_replay-1.0.1.dist-info/WHEEL
astro_pi_replay-1.0.1.dist-info/entry_points.txt
astro_pi_replay-1.0.1.dist-info/top_level.txt
astro_pi_replay-1.0.1.dist-info/RECORD
