Metadata-Version: 2.1
Name: astro_pi_replay
Version: 1.0.1
Summary: A CLI to replay historic data from previous ISS missions.
Author-email: Geraint Ballinger <geraint.ballinger@raspberrypi.org>
License: Copyright 2023- Raspberry Pi Foundation
Project-URL: Homepage, https://github.com/astro-pi/Astro-Pi-Replay
Classifier: Programming Language :: Python :: 3
Classifier: Operating System :: OS Independent
Requires-Python: >=3.9
License-File: LICENCE.txt
Requires-Dist: colorzero >=2.0
Requires-Dist: requests >=2.31
Requires-Dist: skyfield >=1.46
Requires-Dist: typing-extensions >=4.7.1
Requires-Dist: tqdm >=4.66.0
Requires-Dist: setuptools >=61.0
Requires-Dist: exif >=1.6.0
Requires-Dist: piexif ==1.1.3
Requires-Dist: opencv-python ~=4.6
Requires-Dist: scipy ==1.8.1 ; python_version < "3.11"
Requires-Dist: scipy >=1.11.2 ; python_version >= "3.11"
Requires-Dist: Pillow ==10.0.0 ; sys_platform != "emscripten"
Requires-Dist: pandas ==2.0.3 ; sys_platform != "emscripten" and python_version < "3.12"
Requires-Dist: numpy ==1.24.3 ; sys_platform != "emscripten" and python_version < "3.12"
Requires-Dist: pandas ==2.1.1 ; sys_platform != "emscripten" and python_version >= "3.12"
Requires-Dist: numpy ==1.26.0 ; sys_platform != "emscripten" and python_version >= "3.12"
Requires-Dist: pandas >=2.1.1 ; sys_platform == "emscripten"
Requires-Dist: Pillow >=10.0.0 ; sys_platform == "emscripten"
Requires-Dist: numpy >=1.26.0 ; sys_platform == "emscripten"
